dbhub/__init__.py
dbhub/dbhub.py
dbhub/exceptions.py
dbhub-0.5.2.dist-info/LICENCE
dbhub-0.5.2.dist-info/METADATA
dbhub-0.5.2.dist-info/WHEEL
dbhub-0.5.2.dist-info/top_level.txt
dbhub-0.5.2.dist-info/RECORD
