Metadata-Version: 2.1
Name: dbhub
Version: 0.5.2
Summary: Package to create db in one-click
Home-page: https://github.com/Noxormy/dbhub_pip
Author: Noxormy
Author-email: noxormy@gmail.com
License: UNKNOWN
Platform: UNKNOWN
Classifier: Programming Language :: Python :: 3
Classifier: License :: OSI Approved :: MIT License
Classifier: Operating System :: OS Independent
Requires-Python: >=3.6
License-File: LICENCE
Requires-Dist: requests (>=2.2.0)
Requires-Dist: easydict (>=1.9.0)
